bgRemoverApp/__init__.py
bgRemoverApp/removeBG.py
bgRemoverApp/tracer/EfficientNet.py
bgRemoverApp/tracer/att_modules.py
bgRemoverApp/tracer/config.py
bgRemoverApp/tracer/conv_modules.py
bgRemoverApp/tracer/effi_utils.py
bgRemoverApp/tracer/tracer.py
bgRemoverApp/tracer/utils.py
bgRemoverApp/u2net/model.py
bgRemoverApp/u2net/utils.py
bgRemoverApp-1.31.dist-info/METADATA
bgRemoverApp-1.31.dist-info/WHEEL
bgRemoverApp-1.31.dist-info/top_level.txt
bgRemoverApp-1.31.dist-info/RECORD
