Metadata-Version: 2.1
Name: bgRemoverApp
Version: 1.31
Summary: Background Remover App
Home-page: https://github.com/kos94ok/bgRemoverApp
Author: kos94ok
Author-email: mirmen999@mail.ru
License: UNKNOWN
Platform: UNKNOWN
Classifier: Programming Language :: Python :: 3.9
Classifier: Programming Language :: Python :: 3.8
Classifier: Programming Language :: Python :: 3.7
Classifier: License :: OSI Approved :: MIT License
Classifier: Operating System :: OS Independent
Requires-Python: >=3.7
Requires-Dist: torch
Requires-Dist: torchvision
Requires-Dist: numpy
Requires-Dist: Pillow
Requires-Dist: scikit-image
Requires-Dist: opencv-python
